anavid_sl/__init__.py
anavid_sl/core.py
anavid_sl/utils.py
anavid-0.1.dist-info/METADATA
anavid-0.1.dist-info/WHEEL
anavid-0.1.dist-info/top_level.txt
anavid-0.1.dist-info/RECORD
